{"cameraMode":{"drawMode":0,"name":"Shaded","section":"Shading Mode"},"sceneLighting":true,"audioPlay":false,"sceneViewState":{"showFog":true,"showMaterialUpdate":false,"showSkybox":true,"showFlares":true,"showImageEffects":true,"showParticleSystems":true},"in2DMode":false,"pivot":{"x":53.80000305175781,"y":3.685000419616699,"z":241.09625244140626},"rotation":{"x":0.07277219742536545,"y":-0.9271253347396851,"z":0.25254857540130618,"w":0.2671368420124054},"size":200.05186462402345,"orthographic":false}